cdd_python/__init__.py
cdd_python/engine.py
cdd_python/bin/ratel-linux-x64
cdd_python/bin/ratel-macos-x64
cdd_python/bin/ratel-windows-x64.exe
cdd_python-0.6.0a0.dist-info/METADATA
cdd_python-0.6.0a0.dist-info/WHEEL
cdd_python-0.6.0a0.dist-info/top_level.txt
cdd_python-0.6.0a0.dist-info/RECORD
