Metadata-Version: 2.4
Name: cdd-python
Version: 0.6.0a0
Summary: Python adapter for the CDD Security Framework (Ratel Core)
Home-page: https://github.com/cdd-framework/cdd-python
Author: Fabio Meyer<github.com/jemmyx>
Classifier: Programming Language :: Python :: 3
Classifier: License :: OSI Approved :: MIT License
Classifier: Operating System :: OS Independent
Requires-Python: >=3.7
Dynamic: author
Dynamic: classifier
Dynamic: description
Dynamic: description-content-type
Dynamic: home-page
Dynamic: requires-python
Dynamic: summary
